VSMD/VSMD1X6.py
VSMD/__init__.py
VSMD/canMsgHandler.py
VSMD/example.py
VSMD-0.2.8.dist-info/LICENSE
VSMD-0.2.8.dist-info/METADATA
VSMD-0.2.8.dist-info/WHEEL
VSMD-0.2.8.dist-info/top_level.txt
VSMD-0.2.8.dist-info/RECORD
