Metadata-Version: 2.1
Name: VSMD
Version: 0.2.8
Summary: Controller for VSMD CAN motor
Home-page: https://github.com/JChrysanthemum/VSMD
Author: jiangxt
Author-email: 624099049@qq.com
License: UNKNOWN
Platform: UNKNOWN
Classifier: Programming Language :: Python :: 3
Classifier: License :: OSI Approved :: MIT License
Classifier: License :: OSI Approved :: GNU General Public License v3 (GPLv3)
Classifier: Operating System :: OS Independent
Requires-Python: >=3.5
Requires-Dist: python-can
